<?xml version="1.0" encoding="UTF-8" standalone="yes"?>
<response>

<resources name="response">
  <resource>
    <str name="dc:title">Más de 400 personas participan en los cursos organizados por el Ayuntamiento a través del campussantanderempende durante el primer cuatrimestre del año</str>
    <str name="dc:description">
La concejala en  funciones de Empleo y Desarrollo Empresarial  precisa que, durante los primeros meses del año, se han ofertado un total de 16 cursos. &lt;/br&gt;
En este sentido, explica que la temática de los cursos se ha dividido en 5 grandes categorías: Empleo y mercado laboral, TICS e Innovación, Emprendimiento y dos más, una relacionada con el programa de becas Acceso y Redes que se gestionan desde la Agencia de Desarrollo y la última Escenarios, relacionada con Comercio electrónico y  Redes Sociales. &lt;/br&gt;
Díaz-Domínguez hace hincapié en que la plataforma, una de las medidas incluida en el Plan de estímulo de la actividad económica y el empleo de 2012, ofrece formación gratuita, tanto a trabajadores en activo, a los que facilita su reciclaje profesional, como a personas en situación de desempleo, promoviendo en este caso la mejora de la formación. &lt;/br&gt;

</str>
    <str name="dc:date">Sun, 31 May 2015 09:02:00 GMT</str>
    <str name="dc:source">http://portal.ayto-santander.es/santander_inet/Ficha?itemId=9621472</str>
    <date name="dc:modified">2015-09-22T06:32:37.331Z</date>
    <str name="uri">http://datos.santander.es/api/datos/noticias_empleo/mas-de-400-personas-participan-en-los-cursos-organizados-por-el-ayuntamiento-a-traves-del-campussantanderempende-durante-el-primer-cuatrimestre-del-ano</str></resource>
  <resource>
    <str name="dc:title">Más de 2.500 personas se forman en nuevas tecnologías a través de los telecentros municipales durante los cinco primeros meses del año </str>
    <str name="dc:description">
La concejala en funciones de Empleo y Desarrollo Empresarial explica que, entre los meses de enero y mayo, se ofertaron un total de 521 cursos, todos ellos gratuitos y de una semana de duración.&lt;br&gt;
En este sentido, precisa que fueron los de informática básica, con 501 alumnos, los más solicitados, junto con los de internet y correo electrónico (471), informática avanzada (242) y el taller de redes sociales (174).&lt;br&gt;
"A través de los cursos de informática, no sólo facilitamos el acercamiento de las nuevas tecnologías a todos los vecinos, sino que, en el caso de las personas en situación de desempleo, hacemos posible su reciclaje profesional y, con ello, contribuimos a mejorar su acceso al mercado laboral", subraya la edil.&lt;br&gt;
De hecho, incide en que el 45 por ciento de los alumnos que asistieron a los cursos eran desempleados; un 30 por ciento jubilados y el 15 por ciento trabajadores en activo.&lt;br&gt;

</str>
    <str name="dc:date">Fri, 05 Jun 2015 14:47:00 GMT</str>
    <str name="dc:source">http://portal.ayto-santander.es/santander_inet/Ficha?itemId=9640242</str>
    <date name="dc:modified">2015-09-22T06:32:37.329Z</date>
    <str name="uri">http://datos.santander.es/api/datos/noticias_empleo/mas-de-2-500-personas-se-forman-en-nuevas-tecnologias-a-traves-de-los-telecentros-municipales-durante-los-cinco-primeros-meses-del-ano</str></resource>
  <resource>
    <str name="dc:title">Recibidas 1.250 candidaturas para la contratación de desempleados a través de la II fase del programa corporaciones locales 2015 </str>
    <str name="dc:description">
La concejala en funciones de Empleo y Desarrollo Empresarial recuerda que las contrataciones para los cuatro programas ofertados que se realizarán en la primera quincena del mes de agosto, a través de la empresa municipal Santurban S.A, en colaboración con el Servicio Cántabro de Empleo y el Fondo Social Europeo, supondrán una inversión total de 543.600 euros. &lt;/br&gt;
Díaz-Domínguez anuncia que la lista de candidatos admitidos y excluidos se publicará la segunda semana de junio en el tablón de anuncios de la Agencia de Desarrollo de Santander y en la web del Ayuntamiento de Santander, así como en la página web de la Agencia de Desarrollo de Santander.&lt;/br&gt;

</str>
    <str name="dc:date">Mon, 08 Jun 2015 09:38:00 GMT</str>
    <str name="dc:source">http://portal.ayto-santander.es/santander_inet/Ficha?itemId=9650768</str>
    <date name="dc:modified">2015-09-22T06:32:37.326Z</date>
    <str name="uri">http://datos.santander.es/api/datos/noticias_empleo/recibidas-1-250-candidaturas-para-la-contratacion-de-desempleados-a-traves-de-la-ii-fase-del-programa-corporaciones-locales-2015</str></resource>
  <resource>
    <str name="dc:title">Alumnos de la ESO volverán a convertirse, por unos días, en 'cuidadores' de animales en el minizoo de La Magdalena </str>
    <str name="dc:description">
Con este objetivo, el Consistorio santanderino firmará un nuevo convenio de colaboración con el IES Villajunco, a través del programa 'LaborESO'. &lt;/br&gt;
Se trata de una iniciativa que muestra a los jóvenes diferentes entornos laborales que les ayuden a orientar su futuro académico y profesional. &lt;/br&gt;

</str>
    <str name="dc:date">Mon, 08 Jun 2015 13:04:00 GMT</str>
    <str name="dc:source">http://portal.ayto-santander.es/santander_inet/Ficha?itemId=9651796</str>
    <date name="dc:modified">2015-09-22T06:32:37.324Z</date>
    <str name="uri">http://datos.santander.es/api/datos/noticias_empleo/alumnos-de-la-eso-volveran-a-convertirse-por-unos-dias-en-cuidadores-de-animales-en-el-minizoo-de-la-magdalena</str></resource>
  <resource>
    <str name="dc:title">El Ayuntamiento abrirá el próximo lunes el plazo de subsanación para las solicitudes de los 70 contratos para desempleados que no cumplen los requerimientos de las bases</str>
    <str name="dc:description">
La concejala en funciones de Empleo y Desarrollo Empresarial explica que el 63 por ciento de las 1.386 solicitudes recibidas han sido directamente admitidas por presentar correctamente la documentación requerida.&lt;br&gt;
En este sentido, apunta que el 37 por ciento restante dispondrá hasta las 14:30 horas del próximo 17 de junio para entregar la documentación pendiente en la Agencia de Desarrollo de Santander, ubicada en el número 30 de la calle Magallanes, junto con el correspondiente anexo de subsanación.&lt;br&gt;
El Consistorio santanderino publicará mañana, tanto en la web de la Agencia de Desarrollo como en la del propio Ayuntamiento la lista de solicitudes admitidas (872) y la de rechazadas (514), así como el anexo de subsanación.&lt;br&gt;

</str>
    <str name="dc:date">Thu, 11 Jun 2015 14:01:00 GMT</str>
    <str name="dc:source">http://portal.ayto-santander.es/santander_inet/Ficha?itemId=9666312</str>
    <date name="dc:modified">2015-09-22T06:32:37.322Z</date>
    <str name="uri">http://datos.santander.es/api/datos/noticias_empleo/el-ayuntamiento-abrira-el-proximo-lunes-el-plazo-de-subsanacion-para-las-solicitudes-de-los-70-contratos-para-desempleados-que-no-cumplen-los-requerimientos-de-las-bases</str></resource>
  <resource>
    <str name="dc:title">El Ayuntamiento pondrá en marcha el próximo 22 de junio "En chanclas", un nuevo espacio de ocio y tiempo libre</str>
    <str name="dc:description">
La concejala en funciones de Empleo y Desarrollo Empresarial explica que es un proyecto pensado para ofrecer una alternativa de ocio infantil  y facilitar así  la conciliación familiar y laboral.&lt;br&gt;
En este sentido, avanza que el programa tendrá una duración de seis semanas, que abarcarán desde el lunes 22 de junio hasta el jueves 30 de julio en horario de mañana, de 9:00 a 14:00 horas.&lt;br&gt;
Díaz-Domínguez hace hincapié de que se trata de una actividad gratuita dirigida a niños de 6 a 12 años, que se desarrollará mediante semanas temáticas.&lt;br&gt;

</str>
    <str name="dc:date">Fri, 12 Jun 2015 14:04:00 GMT</str>
    <str name="dc:source">http://portal.ayto-santander.es/santander_inet/Ficha?itemId=9672058</str>
    <date name="dc:modified">2015-09-22T06:32:37.32Z</date>
    <str name="uri">http://datos.santander.es/api/datos/noticias_empleo/el-ayuntamiento-pondra-en-marcha-el-proximo-22-de-junio-en-chanclas-un-nuevo-espacio-de-ocio-y-tiempo-libre</str></resource>
  <resource>
    <str name="dc:title">30 jóvenes desempleados se forman en nuevas tecnologías para mejorar sus oportunidades de inserción laboral</str>
    <str name="dc:description">
De la Serna ha explicado que el Ayuntamiento viene dirigiendo las acciones de formación para el empleo hacia áreas en las que el equipo de gobierno está volcando su acción y que considera que pueden ofrecer mayores oportunidades de inserción laboral, como es el caso de la innovación tecnológica.&lt;/br&gt;
</str>
    <str name="dc:date">Tue, 16 Jun 2015 18:14:00 GMT</str>
    <str name="dc:source">http://portal.ayto-santander.es/santander_inet/Ficha?itemId=9689072</str>
    <date name="dc:modified">2015-09-22T06:32:37.318Z</date>
    <str name="uri">http://datos.santander.es/api/datos/noticias_empleo/30-jovenes-desempleados-se-forman-en-nuevas-tecnologias-para-mejorar-sus-oportunidades-de-insercion-laboral</str></resource>
  <resource>
    <str name="dc:title">Los telecentros de Santander ofrecerán talleres de informática gratuitos para niños en el mes de julio</str>
    <str name="dc:description">

</str>
    <str name="dc:date">Thu, 18 Jun 2015 19:36:00 GMT</str>
    <str name="dc:source">http://portal.ayto-santander.es/santander_inet/Ficha?itemId=9706216</str>
    <date name="dc:modified">2015-09-22T06:32:37.316Z</date>
    <str name="uri">http://datos.santander.es/api/datos/noticias_empleo/los-telecentros-de-santander-ofreceran-talleres-de-informatica-gratuitos-para-ninos-en-el-mes-de-julio</str></resource>
  <resource>
    <str name="dc:title">El Ayuntamiento y Comisiones Obreras se comprometen a analizar líneas de colaboración conjunta en esta legislatura</str>
    <str name="dc:description">

</str>
    <str name="dc:date">Mon, 22 Jun 2015 21:16:00 GMT</str>
    <str name="dc:source">http://portal.ayto-santander.es/santander_inet/Ficha?itemId=9722178</str>
    <date name="dc:modified">2015-09-22T06:32:37.314Z</date>
    <str name="uri">http://datos.santander.es/api/datos/noticias_empleo/el-ayuntamiento-y-comisiones-obreras-se-comprometen-a-analizar-lineas-de-colaboracion-conjunta-en-esta-legislatura</str></resource>
  <resource>
    <str name="dc:title">El alcalde valora la contribución del Bosch Competence Center a la proyección internacional de Santander</str>
    <str name="dc:description">
El alcalde ha destacado que se trata de un centro de innovación, en consonancia con el modelo de ciudad en el que trabaja Santander, que ha supuesto una elevada inversión, cercana al millón y medio de euros, con lo que ello conlleva de impulso al crecimiento económico y a la generación de empleo.&lt;/br&gt;
</str>
    <str name="dc:date">Mon, 22 Jun 2015 21:22:00 GMT</str>
    <str name="dc:source">http://portal.ayto-santander.es/santander_inet/Ficha?itemId=9722207</str>
    <date name="dc:modified">2015-09-22T06:32:37.312Z</date>
    <str name="uri">http://datos.santander.es/api/datos/noticias_empleo/el-alcalde-valora-la-contribucion-del-bosch-competence-center-a-la-proyeccion-internacional-de-santander</str></resource>
  <resource>
    <str name="dc:title">El Ayuntamiento y UGT explorarán líneas de colaboración para potenciar la economía social en Santander</str>
    <str name="dc:description">

</str>
    <str name="dc:date">Tue, 23 Jun 2015 20:16:00 GMT</str>
    <str name="dc:source">http://portal.ayto-santander.es/santander_inet/Ficha?itemId=9726571</str>
    <date name="dc:modified">2015-09-22T06:32:37.31Z</date>
    <str name="uri">http://datos.santander.es/api/datos/noticias_empleo/el-ayuntamiento-y-ugt-exploraran-lineas-de-colaboracion-para-potenciar-la-economia-social-en-santander</str></resource>
  <resource>
    <str name="dc:title">El Ayuntamiento da a conocer a 30 emprendedores y empresas modelos de negocio digital útiles para sus proyectos empresariales</str>
    <str name="dc:description">

</str>
    <str name="dc:date">Fri, 26 Jun 2015 20:54:00 GMT</str>
    <str name="dc:source">http://portal.ayto-santander.es/santander_inet/Ficha?itemId=9747826</str>
    <date name="dc:modified">2015-09-22T06:32:37.308Z</date>
    <str name="uri">http://datos.santander.es/api/datos/noticias_empleo/el-ayuntamiento-da-a-conocer-a-30-emprendedores-y-empresas-modelos-de-negocio-digital-utiles-para-sus-proyectos-empresariales</str></resource>
  <resource>
    <str name="dc:title">El Ayuntamiento abre la convocatoria de ayudas para empresas y emprendedores 2015</str>
    <str name="dc:description">
Contará con un presupuesto global de 80.000 euros.&lt;/BR&gt; 
</str>
    <str name="dc:date">Mon, 29 Jun 2015 21:14:00 GMT</str>
    <str name="dc:source">http://portal.ayto-santander.es/santander_inet/Ficha?itemId=9750662</str>
    <date name="dc:modified">2015-09-22T06:32:37.304Z</date>
    <str name="uri">http://datos.santander.es/api/datos/noticias_empleo/el-ayuntamiento-abre-la-convocatoria-de-ayudas-para-empresas-y-emprendedores-2015</str></resource>
  <resource>
    <str name="dc:title">El Ayuntamiento y la Fundación Caja Cantabria mejoran la formación de 72 jóvenes para faciltar su acceso al mercado laboral</str>
    <str name="dc:description">

</str>
    <str name="dc:date">Thu, 02 Jul 2015 10:01:00 GMT</str>
    <str name="dc:source">http://portal.ayto-santander.es/santander_inet/Ficha?itemId=9761894</str>
    <date name="dc:modified">2015-09-22T06:32:37.303Z</date>
    <str name="uri">http://datos.santander.es/api/datos/noticias_empleo/el-ayuntamiento-y-la-fundacion-caja-cantabria-mejoran-la-formacion-de-72-jovenes-para-faciltar-su-acceso-al-mercado-laboral</str></resource>
  <resource>
    <str name="dc:title">El Ayuntamiento anima a AMEC a sumarse a las becas Acceso y Redes y la Guía de Responsabilidad Social</str>
    <str name="dc:description">

</str>
    <str name="dc:date">Fri, 10 Jul 2015 09:24:00 GMT</str>
    <str name="dc:source">http://portal.ayto-santander.es/santander_inet/Ficha?itemId=9794520</str>
    <date name="dc:modified">2015-09-22T06:32:37.301Z</date>
    <str name="uri">http://datos.santander.es/api/datos/noticias_empleo/el-ayuntamiento-anima-a-amec-a-sumarse-a-las-becas-acceso-y-redes-y-la-guia-de-responsabilidad-social</str></resource>
  <resource>
    <str name="dc:title">El Ayuntamiento y "la Caixa" premian los mejores proyectos emprendedores de estudiantes de Bachillerato y FP</str>
    <str name="dc:description">

</str>
    <str name="dc:date">Fri, 10 Jul 2015 21:07:00 GMT</str>
    <str name="dc:source">http://portal.ayto-santander.es/santander_inet/Ficha?itemId=9796775</str>
    <date name="dc:modified">2015-09-22T06:32:37.299Z</date>
    <str name="uri">http://datos.santander.es/api/datos/noticias_empleo/el-ayuntamiento-y-la-caixa-premian-los-mejores-proyectos-emprendedores-de-estudiantes-de-bachillerato-y-fp</str></resource>
  <resource>
    <str name="dc:title">Los telecentros programan nuevos talleres de informática para niños en agosto</str>
    <str name="dc:description">
El Ayuntamiento pretende fomentar el conocimiento de las herramientas informáticas por parte de los más pequeños, al tiempo que facilita a las familias acciones dirigidas a la conciliación laboral y familiar.&lt;/br&gt;
</str>
    <str name="dc:date">Wed, 15 Jul 2015 20:17:00 GMT</str>
    <str name="dc:source">http://portal.ayto-santander.es/santander_inet/Ficha?itemId=9816269</str>
    <date name="dc:modified">2015-09-22T06:32:37.297Z</date>
    <str name="uri">http://datos.santander.es/api/datos/noticias_empleo/los-telecentros-programan-nuevos-talleres-de-informatica-para-ninos-en-agosto</str></resource>
  <resource>
    <str name="dc:title">Un mural dedicado al espacio decora los muros del colegio Sardinero tras las obras de mejora</str>
    <str name="dc:description">

</str>
    <str name="dc:date">Thu, 23 Jul 2015 15:17:00 GMT</str>
    <str name="dc:source">http://portal.ayto-santander.es/santander_inet/Ficha?itemId=9847260</str>
    <date name="dc:modified">2015-09-22T06:32:37.295Z</date>
    <str name="uri">http://datos.santander.es/api/datos/noticias_empleo/un-mural-dedicado-al-espacio-decora-los-muros-del-colegio-sardinero-tras-las-obras-de-mejora</str></resource>
  <resource>
    <str name="dc:title">El Ayuntamiento reúne a los firmantes del Pacto por el Empleo para priorizar medidas</str>
    <str name="dc:description">

</str>
    <str name="dc:date">Tue, 28 Jul 2015 09:28:00 GMT</str>
    <str name="dc:source">http://portal.ayto-santander.es/santander_inet/Ficha?itemId=9866477</str>
    <date name="dc:modified">2015-09-22T06:32:37.293Z</date>
    <str name="uri">http://datos.santander.es/api/datos/noticias_empleo/el-ayuntamiento-reune-a-los-firmantes-del-pacto-por-el-empleo-para-priorizar-medidas</str></resource>
  <resource>
    <str name="dc:title">Cerca de 500 desempleados de Santander han recibido orientación personalizada y formación para su inserción laboral</str>
    <str name="dc:description">
Se han impartido 26 cursos de Nuevas Tecnologías de la Información y la Comunicación, 7 de certificado de higiene alimentaria, 5 de lengua de signos, 5 de calidad, 5 de emprendimiento y 8 de certificado electrónico y firma digital, 15 de inglés y 11 de Prevención de Riesgos Laborales con operador/a de carretilla elevadora. &lt;br.&gt;
</str>
    <str name="dc:date">Sun, 02 Aug 2015 12:29:00 GMT</str>
    <str name="dc:source">http://portal.ayto-santander.es/santander_inet/Ficha?itemId=9893306</str>
    <date name="dc:modified">2015-09-22T06:32:37.292Z</date>
    <str name="uri">http://datos.santander.es/api/datos/noticias_empleo/cerca-de-500-desempleados-de-santander-han-recibido-orientacion-personalizada-y-formacion-para-su-insercion-laboral</str></resource>
  <resource>
    <str name="dc:title">Abierto el plazo de inscripción para la VII edición del programa 'Conduce tu futuro'</str>
    <str name="dc:description">
Promueve la inserción laboral de personas desempleadas del municipio mediante la financiación económica del carné de conducir &lt;/br&gt;
</str>
    <str name="dc:date">Fri, 07 Aug 2015 13:29:00 GMT</str>
    <str name="dc:source">http://portal.ayto-santander.es/santander_inet/Ficha?itemId=9912782</str>
    <date name="dc:modified">2015-09-22T06:32:37.29Z</date>
    <str name="uri">http://datos.santander.es/api/datos/noticias_empleo/abierto-el-plazo-de-inscripcion-para-la-vii-edicion-del-programa-conduce-tu-futuro-</str></resource>
  <resource>
    <str name="dc:title">El Ayuntamiento destina 100.000 euros al proyecto de empleabilidad para personas en riesgo de exclusión social que desarrolla junto a la Fundación Caja Cantabria</str>
    <str name="dc:description">
De la Serna ha remarcado que impulsar la creación de empleo es una "absoluta prioridad" para el equipo de gobierno &lt;/br&gt;
</str>
    <str name="dc:date">Sat, 08 Aug 2015 09:25:00 GMT</str>
    <str name="dc:source">http://portal.ayto-santander.es/santander_inet/Ficha?itemId=9924288</str>
    <date name="dc:modified">2015-09-22T06:32:37.288Z</date>
    <str name="uri">http://datos.santander.es/api/datos/noticias_empleo/el-ayuntamiento-destina-100-000-euros-al-proyecto-de-empleabilidad-para-personas-en-riesgo-de-exclusion-social-que-desarrolla-junto-a-la-fundacion-caja-cantabria</str></resource>
  <resource>
    <str name="dc:title">Los telecentros de Santander ofertarán en septiembre más de 700 plazas en 72 cursos</str>
    <str name="dc:description">
Los cursos y talleres, de duración semanal en sesiones de dos horas diarias, se desarrollarán en horario de mañana en nueve telecentros repartidos por toda la ciudad
</str>
    <str name="dc:date">Fri, 14 Aug 2015 13:26:00 GMT</str>
    <str name="dc:source">http://portal.ayto-santander.es/santander_inet/Ficha?itemId=9942470</str>
    <date name="dc:modified">2015-09-22T06:32:37.287Z</date>
    <str name="uri">http://datos.santander.es/api/datos/noticias_empleo/los-telecentros-de-santander-ofertaran-en-septiembre-mas-de-700-plazas-en-72-cursos</str></resource>
  <resource>
    <str name="dc:title">El Servicio de Orientación Laboral de las Unidades de Trabajo Social ha atendido a 83 personas desde su puesta en marcha </str>
    <str name="dc:description">
Se trata de un servicio de orientación laboral dirigido a los usuarios de los servicios sociales de las distintas Unidades de Trabajo Social, UTS, del municipio, que se ofrece en los Centros Cívicos de Cueto, Peñacastillo, Cazoña, Monte, Calle Alta y General Dávila &lt;/br&gt;
</str>
    <str name="dc:date">Wed, 19 Aug 2015 18:27:00 GMT</str>
    <str name="dc:source">http://portal.ayto-santander.es/santander_inet/Ficha?itemId=9966452</str>
    <date name="dc:modified">2015-09-22T06:32:37.285Z</date>
    <str name="uri">http://datos.santander.es/api/datos/noticias_empleo/el-servicio-de-orientacion-laboral-de-las-unidades-de-trabajo-social-ha-atendido-a-83-personas-desde-su-puesta-en-marcha</str></resource>
  <resource>
    <str name="dc:title">El Ayuntamiento pone en marcha un programa de formación y prácticas para desempleados con formación superior</str>
    <str name="dc:description">
Está especializado en la reorientación e inserción laboral, que seleccionará a 40 personas de entre 20 y 45 años de la bolsa de empleo de la Agencia de Desarrollo Local &lt;/br&gt;
</str>
    <str name="dc:date">Thu, 20 Aug 2015 17:20:00 GMT</str>
    <str name="dc:source">http://portal.ayto-santander.es/santander_inet/Ficha?itemId=9971852</str>
    <date name="dc:modified">2015-09-22T06:32:37.283Z</date>
    <str name="uri">http://datos.santander.es/api/datos/noticias_empleo/el-ayuntamiento-pone-en-marcha-un-programa-de-formacion-y-practicas-para-desempleados-con-formacion-superior</str></resource>
  <resource>
    <str name="dc:title">La Federación Empresarial de la Dependencia se sumará al Pacto Territorial para el Empleo de Santander</str>
    <str name="dc:description">
La colaboración del Ayuntamiento y FED Cantabria se extenderá también a otras áreas de la actividad municipal, en particular, al desarrollo del segundo Plan de Atención para las Personas con Discapacidad &lt;/br&gt;
</str>
    <str name="dc:date">Sun, 30 Aug 2015 12:39:00 GMT</str>
    <str name="dc:source">http://portal.ayto-santander.es/santander_inet/Ficha?itemId=10028099</str>
    <date name="dc:modified">2015-09-22T06:32:37.282Z</date>
    <str name="uri">http://datos.santander.es/api/datos/noticias_empleo/la-federacion-empresarial-de-la-dependencia-se-sumara-al-pacto-territorial-para-el-empleo-de-santander</str></resource>
  <resource>
    <str name="dc:title">Las becas Redes y Acceso duplican ya las concedidas en todo 2014</str>
    <str name="dc:description">
La concejala de Empleo y Desarrollo Empresarial destaca la importancia de este tipo de iniciativas para mejorar la empleabilidad de los jóvenes recién titulados y aumentar sus posibilidades de inserción &lt;/br&gt;
</str>
    <str name="dc:date">Sat, 05 Sep 2015 11:16:00 GMT</str>
    <str name="dc:source">http://portal.ayto-santander.es/santander_inet/Ficha?itemId=10062086</str>
    <date name="dc:modified">2015-09-22T06:32:37.28Z</date>
    <str name="uri">http://datos.santander.es/api/datos/noticias_empleo/las-becas-redes-y-acceso-duplican-ya-las-concedidas-en-todo-2014</str></resource>
  <resource>
    <str name="dc:title">Santander abre su Telecentro 3.0, que ofrecerá formación en nuevas tecnologías de alto nivel</str>
    <str name="dc:description">
Cuenta con el espacio 'Oportunidades', para ayudar a que las ideas de los usuarios se conviertan en proyectos reales y en nuevas iniciativas económicas &lt;/br&gt;
</str>
    <str name="dc:date">Fri, 18 Sep 2015 21:35:00 GMT</str>
    <str name="dc:source">http://portal.ayto-santander.es/santander_inet/Ficha?itemId=10117120</str>
    <date name="dc:modified">2015-09-22T06:32:37.278Z</date>
    <str name="uri">http://datos.santander.es/api/datos/noticias_empleo/santander-abre-su-telecentro-3-0-que-ofrecera-formacion-en-nuevas-tecnologias-de-alto-nivel</str></resource>
  <resource>
    <str name="dc:title">Seguridad en internet, redes sociales y el uso de dispositivos Android, principales ejes de los cursos de octubre en los telecentros</str>
    <str name="dc:description">
En total se ofertan 680 plazas en 70 cursos que ya tienen abiertas las inscripciones&lt;/br&gt;
</str>
    <str name="dc:date">Mon, 21 Sep 2015 17:08:00 GMT</str>
    <str name="dc:source">http://portal.ayto-santander.es/santander_inet/Ficha?itemId=10131401</str>
    <date name="dc:modified">2015-09-22T06:32:37.277Z</date>
    <str name="uri">http://datos.santander.es/api/datos/noticias_empleo/seguridad-en-internet-redes-sociales-y-el-uso-de-dispositivos-android-principales-ejes-de-los-cursos-de-octubre-en-los-telecentros</str></resource>
</resources>
</response>
